ksmi/__init__.py
ksmi/__main__.py
ksmi/add_env.py
ksmi/copy_id.py
ksmi/kairos_smi.py
ksmi-0.2.1.dist-info/LICENSE
ksmi-0.2.1.dist-info/METADATA
ksmi-0.2.1.dist-info/WHEEL
ksmi-0.2.1.dist-info/top_level.txt
ksmi-0.2.1.dist-info/RECORD
